LICENSE
MANIFEST.in
README.rst
setup.py
config_enhance/__init__.py
config_enhance.egg-info/PKG-INFO
config_enhance.egg-info/SOURCES.txt
config_enhance.egg-info/dependency_links.txt
config_enhance.egg-info/top_level.txt
config_enhance.egg-info/zip-safe