Metadata-Version: 1.1
Name: config-enhance
Version: 1.2.2
Summary: Provide reuse to ConfigParser files.
Home-page: https://github.com/zillow/config-enhance
Author: Jonathan Ultis
Author-email: jonathanu@zillow.com
License: # Copyright (c) 2012 Zillow
